ucid_api/__init__.py
ucid_api/ucid.py
ucid_api/constant/__init__.py
ucid_api/constant/ucidconstants.py
ucid_api/exception/__init__.py
ucid_api/exception/ucid_exception.py
ucid_api/utils/__init__.py
ucid_api/utils/header_validate.py
ucid_api/utils/utils.py
ucid_api-0.1.8.dist-info/METADATA
ucid_api-0.1.8.dist-info/WHEEL
ucid_api-0.1.8.dist-info/top_level.txt
ucid_api-0.1.8.dist-info/RECORD
