Metadata-Version: 2.1
Name: ucid-api
Version: 0.1.8
Summary: ucid api calling library
Home-page: https://medium-multiply.readthedocs.io/
Author: Mritunjay Kumar
Author-email: mritunjaykr583@gmail.com
License: DELIVERY
Platform: UNKNOWN
Classifier: Intended Audience :: Developers
Classifier: License :: OSI Approved :: MIT License
Classifier: Programming Language :: Python
Classifier: Programming Language :: Python :: 3.8
Classifier: Programming Language :: Python :: 3.9
Classifier: Operating System :: OS Independent
Requires-Dist: requests (==2.28.1)
Requires-Dist: urllib3 (==1.26.11)
